psx_dashboard/psx_dashboard.py
psx_dashboard/psx_fundamental_analysis.py
psx_dashboard/psx_price_and_volume.py
psx_dashboard/KMI30/kmi30_companies.csv
psx_dashboard_mwbk-0.1.0.dist-info/licenses/LICENSE.txt
psx_dashboard_mwbk-0.1.0.dist-info/METADATA
psx_dashboard_mwbk-0.1.0.dist-info/WHEEL
psx_dashboard_mwbk-0.1.0.dist-info/top_level.txt
psx_dashboard_mwbk-0.1.0.dist-info/RECORD
