Metadata-Version: 2.4
Name: psx-dashboard-MWBK
Version: 0.1.0
Summary: A Streamlit dashboard for PSX stock data, including price history and fundamental analysis.
Author-email: Eebee16 <ebbutt786@gmail.com>
Classifier: Programming Language :: Python :: 3
Classifier: License :: OSI Approved :: MIT License
Classifier: Operating System :: OS Independent
Classifier: Topic :: Office/Business :: Financial :: Investment
Requires-Python: >=3.8
License-File: LICENSE.txt
Requires-Dist: streamlit
Requires-Dist: pandas
Requires-Dist: requests
Requires-Dist: beautifulsoup4
Requires-Dist: plotly
Requires-Dist: numpy
Dynamic: license-file
